ramslibs/__init__.py
ramslibs/_version.py
ramslibs/data_tools.py
ramslibs/plotting_tools.py
ramslibs/thermo.py
ramslibs/xarray.py
ramslibs-0.6.7.dist-info/LICENSE
ramslibs-0.6.7.dist-info/METADATA
ramslibs-0.6.7.dist-info/WHEEL
ramslibs-0.6.7.dist-info/top_level.txt
ramslibs-0.6.7.dist-info/RECORD
