Metadata-Version: 2.1
Name: ramslibs
Version: 0.6.7
Summary: Set of tools for working with RAMS data
Home-page: https://github.com/lsterzinger/ramslibs
Author: Lucas Sterzinger
Author-email: lsterzinger@ucdavis.edu
License: UNKNOWN
Platform: UNKNOWN
Classifier: License :: OSI Approved :: MIT License
Classifier: Intended Audience :: Science/Research
Classifier: Topic :: Scientific/Engineering :: Atmospheric Science
Classifier: Development Status :: 4 - Beta
License-File: LICENSE
Requires-Dist: pyrams
